helpers/__init__.py
helpers/url.py
rawDataLoader/__init__.py
rawDataLoader/date_partitioned_raw_data_loader.py
rawDataLoader/raw_data_loader.py
aicns_raw_data_loader-0.1.0.dist-info/LICENSE
aicns_raw_data_loader-0.1.0.dist-info/METADATA
aicns_raw_data_loader-0.1.0.dist-info/WHEEL
aicns_raw_data_loader-0.1.0.dist-info/top_level.txt
aicns_raw_data_loader-0.1.0.dist-info/RECORD
